pip_add/__init__.py
pip_add/cli.py
pip_add/utils.py
pip_add-0.2.5.dist-info/LICENSE
pip_add-0.2.5.dist-info/METADATA
pip_add-0.2.5.dist-info/WHEEL
pip_add-0.2.5.dist-info/entry_points.txt
pip_add-0.2.5.dist-info/top_level.txt
pip_add-0.2.5.dist-info/RECORD
