Metadata-Version: 2.1
Name: pip-add
Version: 0.2.5
Summary: A modern Python package manager that combines pip install with requirements.txt management. Supports Python 3.11, 3.12, and 3.13.
Home-page: https://github.com/PacNPal/pip-add
Author: PacNPal
Author-email: pac@pacnp.al
Classifier: Development Status :: 4 - Beta
Classifier: Environment :: Console
Classifier: Intended Audience :: Developers
Classifier: Intended Audience :: Information Technology
Classifier: Intended Audience :: System Administrators
Classifier: License :: OSI Approved :: MIT License
Classifier: Natural Language :: English
Classifier: Operating System :: OS Independent
Classifier: Programming Language :: Python :: 3
Classifier: Programming Language :: Python :: 3.11
Classifier: Programming Language :: Python :: 3.12
Classifier: Programming Language :: Python :: 3.13
Classifier: Programming Language :: Python :: Implementation :: CPython
Classifier: Topic :: Software Development :: Libraries :: Python Modules
Classifier: Topic :: System :: Installation/Setup
Classifier: Topic :: System :: Software Distribution
Classifier: Topic :: System :: Systems Administration
Classifier: Topic :: Utilities
Requires-Python: >=3.11
License-File: LICENSE
Requires-Dist: pip
Requires-Dist: setuptools
